poetry_moment/__init__.py
poetry_moment/core.py
poetry_moment/docs.py
poetry_moment-0.0.6.dist-info/LICENSE
poetry_moment-0.0.6.dist-info/METADATA
poetry_moment-0.0.6.dist-info/WHEEL
poetry_moment-0.0.6.dist-info/RECORD
