Metadata-Version: 2.1
Name: poetry-moment
Version: 0.0.6
Summary: [诗歌时刻]让诗意，流露此刻。
Author: Yeying-Xingchen
Author-email: yeyingxingchen@yeah.net
Requires-Python: >=3.6
Classifier: Programming Language :: Python :: 3
Classifier: Programming Language :: Python :: 3.6
Classifier: Programming Language :: Python :: 3.7
Classifier: Programming Language :: Python :: 3.8
Classifier: Programming Language :: Python :: 3.9
Classifier: Programming Language :: Python :: 3.10
Classifier: Programming Language :: Python :: 3.11
Classifier: Programming Language :: Python :: 3.12
Requires-Dist: apicat (>=0.0.2)
Requires-Dist: xhlog (>=0.0.1)
